{"type": "block", "layer": 2, "block": 0, "features": [{"geom": {"pts": [[-230.61930721066892, -117.57423295732588, 7.010831832885742]], "rotateX": 0, "rotateY": 0, "rotateZ": 0, "scale": 0.3}, "model": 0}, {"geom": {"pts": [[-182.07653238996863, -139.53405966237187, 7.175596237182617]], "rotateX": 0, "rotateY": 0, "rotateZ": 0, "scale": 0.3}, "model": 0}, {"geom": {"pts": [[-125.44329509884119, -158.026545307599, 7.529303550720215]], "rotateX": 0, "rotateY": 0, "rotateZ": 0, "scale": 0.3}, "model": 0}, {"geom": {"pts": [[0.5367633644491434, -208.88088083453476, 7.995743274688721]], "rotateX": 0, "rotateY": 0, "rotateZ": 0, "scale": 0.3}, "model": 0}, {"geom": {"pts": [[155.4113306477666, -256.26787530165166, 7.960879802703857]], "rotateX": 0, "rotateY": 0, "rotateZ": 0, "scale": 0.3}, "model": 0}, {"geom": {"pts": [[388.8145616296679, 113.19411559216678, 9.603468894958496]], "rotateX": 0, "rotateY": 0, "rotateZ": 0, "scale": 0.3}, "model": 0}, {"geom": {"pts": [[431.01222599856555, 114.13184146676213, 18.975997924804688]], "rotateX": 0, "rotateY": 0, "rotateZ": 0, "scale": 0.3}, "model": 0}, {"geom": {"pts": [[404.75590150244534, 93.50187222100794, 9.744292259216309]], "rotateX": 0, "rotateY": 0, "rotateZ": 0, "scale": 0.3}, "model": 0}], "featureCount": 8, "startIndex": 0}